{"metadata":{"asset_id":"f63e895b-653a-491a-b31b-728c2bbbe48b","asset_attributes":["job"],"name":"2-applypredictivemodel-Notebook-Job","asset_type":"job","created_at":"2021-06-22T09:37:35Z","description":"","origin_country":"us","owner_id":"1000336120","project_id":"f5e4c561-4231-472d-9c92-f053709ab19a","size":0,"tags":[],"usage":{"last_update_time":1624354655030,"last_updated_at":"2021-06-22T09:37:35Z"}},"entity":{"job":{"asset_ref_type":"notebook","configuration":{"env_id":"jupconda37oce-f5e4c561-4231-472d-9c92-f053709ab19a","file_ref":"","run_results":"log_and_new_notebook","env_type":"notebook","env_variables":[]},"last_run_initiator":"None","last_run_time":"","last_run_status":"None","last_run_status_timestamp":0,"future_scheduled_runs":[],"enable_notifications":true,"project_name":"sales-prediction-using-weather-company-data","asset_ref":"e3688a26-8ef0-42db-b5b0-c6e248429e13"}}}