{"metadata":{"asset_id":"4c2330d9-5203-47ce-8477-da2178957337","asset_attributes":["notebook"],"name":"makedashboarddataScikitlearn","asset_type":"notebook","created_at":"2020-06-15T10:45:08Z","description":"","origin_country":"us","owner_id":"1000331074","project_id":"f7c29471-2853-43d8-a8df-ccdeb2abb0e6","sandbox_id":"f7c29471-2853-43d8-a8df-ccdeb2abb0e6","size":6378190,"tags":["notebook"],"usage":{"last_update_time":1592306146728,"last_updated_at":"2020-06-16T11:15:46Z"}},"entity":{"notebook":{"kernel":{"name":"python3","display_name":"Python 3.6","language":"python"},"originates_from":{"type":"file"},"runtime":{"environment":"jupconda36-f7c29471-2853-43d8-a8df-ccdeb2abb0e6"}}},"attachments":[{"id":"85f4feef-72a8-47fd-b402-e47192e6f41a","version":2,"asset_type":"notebook","name":"attachment for notebook 4c2330d9-5203-47ce-8477-da2178957337","description":"attachment for notebook 4c2330d9-5203-47ce-8477-da2178957337","mime":"application/json","object_key":"notebook/makedashboarddataScikitlearn_hq9PWAOX0.ipynb","create_time":1592217908901,"size":6378190,"is_remote":false,"is_managed":false,"is_referenced":true,"is_object_key_read_only":false,"is_user_provided_path_key":true,"transfer_complete":true,"is_partitioned":false,"complete_time_ticks":1592217908901,"user_data":{},"test_doc":0,"handle":{"key":"notebook/makedashboarddataScikitlearn_hq9PWAOX0.ipynb","upload_id":"done","max_part_num":1},"usage":{"access_count":0,"last_accessor_id":"icp4d-dev","last_access_time":1592217908901}}]}